certbuilder/__init__.py
certbuilder-0.14.2.dist-info/DESCRIPTION.rst
certbuilder-0.14.2.dist-info/METADATA
certbuilder-0.14.2.dist-info/RECORD
certbuilder-0.14.2.dist-info/WHEEL
certbuilder-0.14.2.dist-info/metadata.json
certbuilder-0.14.2.dist-info/top_level.txt
