Metadata-Version: 2.0
Name: certbuilder
Version: 0.14.2
Summary: Creates and signs X.509 certificates
Home-page: https://github.com/wbond/certbuilder
Author: wbond
Author-email: will@wbond.net
License: MIT
Keywords: crypto pki x509 certificate rsa dsa ec
Platform: UNKNOWN
Classifier: Development Status :: 4 - Beta
Classifier: Intended Audience :: Developers
Classifier: License :: OSI Approved :: MIT License
Classifier: Programming Language :: Python :: 2.6
Classifier: Programming Language :: Python :: 2.7
Classifier: Programming Language :: Python :: 3.2
Classifier: Programming Language :: Python :: 3.3
Classifier: Programming Language :: Python :: 3.4
Classifier: Programming Language :: Python :: 3.5
Classifier: Programming Language :: Python :: Implementation :: PyPy
Classifier: Topic :: Security :: Cryptography
Requires-Dist: asn1crypto (>=0.18.1)
Requires-Dist: oscrypto (>=0.16.1)
